fir-dev/bram/bram11_rn.v
// bram behavior code (can't be synthesis)
// 11 words
module bram11_rn 
(
    CLK,
    WE,
    EN,
    Di,
    Do,
    A,
    Resetn
);

    input   wire            CLK;
    input   wire    [3:0]   WE; // write enable 
    input   wire            EN; // read enable
    input   wire    [31:0]  Di;
    output  wire     [31:0]  Do;
    input   wire    [11:0]   A; 
    input   wire            Resetn;

    //  11 words
	reg [31:0] RAM [0:10];
    reg [11:0] r_A;

    always @(posedge CLK) begin
        r_A <= A;
    end

    assign Do = {32{EN & Resetn}} & RAM[r_A>>2];    // read

    reg [31:0] Temp_D;
    always @(posedge CLK) begin
        if (~Resetn) begin
            for (integer i = 0; i < 12; i = i + 1) begin
                RAM[i] <= {32{1'b0}};
            end
        end
        else begin
            if(EN) begin
                if(WE[0]) RAM[A>>2][7:0] <= Di[7:0];
                if(WE[1]) RAM[A>>2][15:8] <= Di[15:8];
                if(WE[2]) RAM[A>>2][23:16] <= Di[23:16];
                if(WE[3]) RAM[A>>2][31:24] <= Di[31:24];
            end
        end
        // $display("%d.",RAM[A>>2]);
    end

endmodule

fir-dev/bram/bram11TB.v
`include "bram11_rn.v"
// bram behavior code (can't be synthesis)
// 11 words
module bram11TB 
();

   reg            CLK;
   reg    [3:0]   WE; // write enable 
   reg            EN; // read enable
   reg    [31:0]  Di;
  wire     [31:0]  Do;
   reg    [11:0]   A; 
   reg             Resetn;        

   bram11_rn DUT1( .CLK(CLK),
                .WE(WE),
                .EN(EN),
                .Di(Di),
                .Do(Do),
                .A(A),
                .Resetn(Resetn));


    initial begin
        $dumpfile("bramTB.vcd");
        $dumpvars();
    end 
    initial begin
        CLK = 0 ;
        forever begin
            #5 CLK = (~CLK);
        end
    end

    initial begin
        // initial
        Resetn = 0;
        Di = 32'd0;
        // RAM [0] = 32'b11111111_00000000_11111111_00000000;
        // RAM [1] = 32'b11111111_00000000_11111111_00000000;
        // RAM [2] = 32'b11111111_00000000_11111111_00000000;
        // RAM [3] = 32'b11111111_00000000_11111111_00000000;
        // RAM [4] = 32'b11111111_00000000_11111111_00000000;
        // RAM [5] = 32'b11111111_00000000_11111111_00000000;
        // RAM [6] = 32'b11111111_00000000_11111111_00000000;
        // RAM [7] = 32'b11111111_00000000_11111111_00000000;
        // RAM [8] = 32'b11111111_00000000_11111111_00000000;
        // RAM [9] = 32'b11111111_00000000_11111111_00000000;
        // RAM [10] = 32'b11111111_00000000_11111111_00000000;
        EN = 1'b0;
        WE = 4'd0 ;

        // $display("RAM[A>>2] = %b.",RAM[A>>2]);
        $display("{32{EN}} = %b.",{32{EN}});
        $display("Do = %b.",Do);
        $display("");

        // read initial value
        $display("Read Test");
        #10 
        Resetn = 1;
        EN = 1'b1;
        WE =  4'd0 ;
        A = 12'b000000000000;
        $display("A = %d.",A);
        $display("A>>2 = %d.",A>>2);
        // $display("RAM[A>>2] = %b.",RAM[A>>2]);
        $display("{32{EN}} = %b.",{32{EN}});
        $display("Do = %b.",Do);
        $display("");

        #10 
        EN = 1'b1;
        WE =  4'd0 ;
        A = 12'b000000000100;
        $display("A = %d.",A);
        $display("A>>2 = %d.",A>>2);
        // $display("RAM[A>>2] = %b.",RAM[A>>2]);
        $display("{32{EN}} = %b.",{32{EN}});
        $display("Do = %b.",Do);
        $display("");

        #10 
        EN = 1'b1;
        WE =  4'd0 ;
        A = 12'b000000001000;
        $display("A = %d.",A);
        $display("A>>2 = %d.",A>>2);
        // $display("RAM[A>>2] = %b.",RAM[A>>2]);
        $display("{32{EN}} = %b.",{32{EN}});
        $display("Do = %b.",Do);
        $display("");

        #10 
        EN = 1'b1;
        WE =  4'd0 ;
        A = 12'b000000001100;
        $display("A = %d.",A);
        $display("A>>2 = %d.",A>>2);
        // $display("RAM[A>>2] = %b.",RAM[A>>2]);
        $display("{32{EN}} = %b.",{32{EN}});
        $display("Do = %b.",Do);
        $display("");

        #10 
        EN = 1'b1;
        WE =  4'd0 ;
        A = 12'b000000101100; //1011
        $display("A = %d.",A);
        $display("A>>2 = %d.",A>>2);
        // $display("RAM[A>>2] = %b.",RAM[A>>2]);
        $display("{32{EN}} = %b.",{32{EN}});
        $display("Do = %b.",Do);
        $display("");

        #10 
        EN = 1'b1;
        WE =  4'd0 ;
        A = 12'b000000110100; //1011
        $display("A = %d.",A);
        $display("A>>2 = %d.",A>>2);
        // $display("RAM[A>>2] = %b.",RAM[A>>2]);
        $display("{32{EN}} = %b.",{32{EN}});
        $display("Do = %b.",Do);
        $display("");
        /////////////////////////////////////////////////////////////////////////////////////
        $display("Write Test");
        // write some value
        #10
        WE=4'b1111;
        Di = 32'b00000000_00000000_00000000_11111111;
        A = 12'b000000000100;
        $display("A = %d.",A);
        $display("A>>2 = %d.",A>>2);
        // $display("RAM[A>>2] = %b.",RAM[A>>2]);
        $display("{32{EN}} = %b.",{32{EN}});
        $display("Do = %b.",Do);
        $display("");
        
        #10
        WE=4'b1111;
        Di = 32'b00000000_00000000_11111111_00000000;
        A = 12'b000000001000;
        $display("A = %d.",A);
        $display("A>>2 = %d.",A>>2);
        // $display("RAM[A>>2] = %b.",RAM[A>>2]);
        $display("{32{EN}} = %b.",{32{EN}});
        $display("Do = %b.",Do);
        $display("");
        

        #10
        WE=4'b1111;
        Di = 32'b00000000_00000000_00000000_11110000;
        A = 12'b000000000100;
        $display("A = %d.",A);
        $display("A>>2 = %d.",A>>2);
        // $display("RAM[A>>2] = %b.",RAM[A>>2]);
        $display("{32{EN}} = %b.",{32{EN}});
        $display("Do = %b.",Do);
        $display("");

        #10
        WE=4'b1111;
        Di = 32'b00000000_00000000_00000000_00001111;
        A = 12'b000000000100;
        $display("A = %d.",A);
        $display("A>>2 = %d.",A>>2);
        // $display("RAM[A>>2] = %b.",RAM[A>>2]);
        $display("{32{EN}} = %b.",{32{EN}});
        $display("Do = %b.",Do);
        $display("");

        #10
        WE=4'b1111;
        Di = 32'b00000000_00000000_00000000_00001101;
        A = 12'b000000110100;
        $display("A = %d.",A);
        $display("A>>2 = %d.",A>>2);
        // $display("RAM[A>>2] = %b.",RAM[A>>2]);
        $display("{32{EN}} = %b.",{32{EN}});
        $display("Do = %b.",Do);
        $display("");

        #10
        WE=4'b1111;
        Di = 32'b00000000_00000000_00000000_00001101;
        A = 12'b000000110100;
        $display("A = %d.",A);
        $display("A>>2 = %d.",A>>2);
        // $display("RAM[A>>2] = %b.",RAM[A>>2]);
        $display("{32{EN}} = %b.",{32{EN}});
        $display("Do = %b.",Do);
        $display("");

        $display("End");
        #10 $finish;
    end

endmodule

fir-dev/bram/bramTB.vcd
$date
	Tue Oct 10 11:09:26 2023
$end
$version
	Icarus Verilog
$end
$timescale
	1s
$end
$scope module bram11TB $end
$var wire 32 ! Do [31:0] $end
$var reg 12 " A [11:0] $end
$var reg 1 # CLK $end
$var reg 32 $ Di [31:0] $end
$var reg 1 % EN $end
$var reg 1 & Resetn $end
$var reg 4 ' WE [3:0] $end
$scope module DUT1 $end
$var wire 12 ( A [11:0] $end
$var wire 1 # CLK $end
$var wire 32 ) Di [31:0] $end
$var wire 32 * Do [31:0] $end
$var wire 1 % EN $end
$var wire 1 & Resetn $end
$var wire 4 + WE [3:0] $end
$var reg 12 , r_A [11:0] $end
$scope begin $ivl_for_loop0 $end
$var integer 32 - i [31:0] $end
$upscope $end
$upscope $end
$upscope $end
$enddefinitions $end
#0
$dumpvars
bx -
bx ,
b0 +
b0 *
b0 )
bx (
b0 '
0&
0%
b0 $
0#
bx "
b0 !
$end
#5
b1100 -
1#
#10
bx !
bx *
0#
b0 "
b0 (
1%
1&
#15
b0 !
b0 *
b0 ,
1#
#20
0#
b100 "
b100 (
#25
b100 ,
1#
#30
0#
b1000 "
b1000 (
#35
b1000 ,
1#
#40
0#
b1100 "
b1100 (
#45
b1100 ,
1#
#50
0#
b101100 "
b101100 (
#55
bx !
bx *
b101100 ,
1#
#60
0#
b110100 "
b110100 (
#65
b110100 ,
1#
#70
0#
b100 "
b100 (
b11111111 $
b11111111 )
b1111 '
b1111 +
#75
b11111111 !
b11111111 *
b100 ,
1#
#80
0#
b1000 "
b1000 (
b1111111100000000 $
b1111111100000000 )
#85
b1111111100000000 !
b1111111100000000 *
b1000 ,
1#
#90
0#
b100 "
b100 (
b11110000 $
b11110000 )
#95
b11110000 !
b11110000 *
b100 ,
1#
#100
0#
b1111 $
b1111 )
#105
b1111 !
b1111 *
1#
#110
0#
b110100 "
b110100 (
b1101 $
b1101 )
#115
bx !
bx *
b110100 ,
1#
