fir-dev/rtl/FIR_Logic.v
// 11 cycle to calculate
module FIR_Logic(   input [31:0] X ,
                    input [31:0] tap ,
                    input CLK,
                    input Resetn,
                    output reg [67:0] Y ,
                    output Done 
                    );
reg [3:0] Done_count ;
always @(posedge CLK or negedge Resetn) begin
    if (~Resetn) begin
        Done_count <= 4'd0;
        Y <= 68'd0 ;
    end else begin
        if (Done) begin
            Y <= (X * tap) ;
            Done_count <= 4'd1;
        end else begin
            Y <= Y + (X * tap) ;
            Done_count <= Done_count+1;
        end
    end
end

assign Done = (Done_count == 4'b1011)? (1):(0) ;

endmodule

fir-dev/fir/rtl/FIR_Logic_TB.v
`include "FIR_Logic.v"
`timescale 1ps/1ps

module FIR_Logic_TB (
);
reg [31:0] X;
reg [31:0] tap;
reg CLK ;
reg Resetn ;
wire Done ;
wire [67:0] Y; 

FIR_Logic DUT1( .X(X) ,
                .tap(tap) ,
                .CLK(CLK),
                .Resetn(Resetn),
                .Y(Y) ,
                .Done(Done) );

    initial begin
        $dumpfile("fir_TB.vcd");
        $dumpvars();
    end


    initial begin
        CLK = 0;
        forever begin
            #5 CLK = (~CLK);
        end
    end

    initial begin
        Resetn = 1 ;
        #10;
        Resetn = 0;

        #10;
        Resetn = 1;
        X = 32'd1;
        tap = 32'd1;
        $display("Y = %d.",Y);
        $monitor("Y = %d.",Y);
        #100;
        #110;
        #10;
        $finish;
    end
    
endmodule

fir-dev/fir/rtl/fir_TB.vcd
$date
	Tue Oct 10 13:14:39 2023
$end
$version
	Icarus Verilog
$end
$timescale
	1ps
$end
$scope module FIR_Logic_TB $end
$var wire 68 ! Y [67:0] $end
$var wire 1 " Done $end
$var reg 1 # CLK $end
$var reg 1 $ Resetn $end
$var reg 32 % X [31:0] $end
$var reg 32 & tap [31:0] $end
$scope module DUT1 $end
$var wire 1 # CLK $end
$var wire 1 $ Resetn $end
$var wire 32 ' X [31:0] $end
$var wire 32 ( tap [31:0] $end
$var wire 1 " Done $end
$var reg 4 ) Done_count [3:0] $end
$var reg 68 * Y [67:0] $end
$upscope $end
$upscope $end
$enddefinitions $end
#0
$dumpvars
bx *
bx )
bx (
bx '
bx &
bx %
1$
0#
x"
bx !
$end
#5
1#
#10
0"
b0 !
b0 *
b0 )
0#
0$
#15
1#
#20
0#
b1 &
b1 (
b1 %
b1 '
1$
#25
b1 )
b1 !
b1 *
1#
#30
0#
#35
b10 )
b10 !
b10 *
1#
#40
0#
#45
b11 )
b11 !
b11 *
1#
#50
0#
#55
b100 )
b100 !
b100 *
1#
#60
0#
#65
b101 )
b101 !
b101 *
1#
#70
0#
#75
b110 )
b110 !
b110 *
1#
#80
0#
#85
b111 )
b111 !
b111 *
1#
#90
0#
#95
b1000 )
b1000 !
b1000 *
1#
#100
0#
#105
b1001 )
b1001 !
b1001 *
1#
#110
0#
#115
b1010 )
b1010 !
b1010 *
1#
#120
0#
#125
1"
b1011 )
b1011 !
b1011 *
1#
#130
0#
#135
0"
b1 )
b1 !
b1 *
1#
#140
0#
#145
b10 )
b10 !
b10 *
1#
#150
0#
#155
b11 )
b11 !
b11 *
1#
#160
0#
#165
b100 )
b100 !
b100 *
1#
#170
0#
#175
b101 )
b101 !
b101 *
1#
#180
0#
#185
b110 )
b110 !
b110 *
1#
#190
0#
#195
b111 )
b111 !
b111 *
1#
#200
0#
#205
b1000 )
b1000 !
b1000 *
1#
#210
0#
#215
b1001 )
b1001 !
b1001 *
1#
#220
0#
#225
b1010 )
b1010 !
b1010 *
1#
#230
0#
#235
1"
b1011 )
b1011 !
b1011 *
1#
